{
  "Search": {
    "ReportType": "rdf",
    "KodeEmiten": "WINE",
    "Year": "2023",
    "SortColumn": "KodeEmiten",
    "SortOrder": "asc",
    "EmitenType": "s",
    "Periode": "audit",
    "indexfrom": 1,
    "pagesize": 12
  },
  "ResultCount": 1,
  "Results": [
    {
      "KodeEmiten": "WINE",
      "File_Modified": "2024-03-26T17:00:11.637",
      "Report_Period": "Audit",
      "Report_Year": "2023",
      "NamaEmiten": "PT Hatten Bali Tbk",
      "Attachments": [
        {
          "Emiten_Code": "WINE",
          "File_ID": "5c935a75-c01f-4f05-946b-2ba22c48aa5f",
          "File_Modified": "2024-03-26T17:00:11.637",
          "File_Name": "Perubahan Aset dan Liabilitas LD 20 pct.pdf",
          "File_Path": "/Portals/0/StaticData/ListedCompanies/Corporate_Actions/New_Info_JSX/Jenis_Informasi/01_Laporan_Keuangan/02_Soft_Copy_Laporan_Keuangan//Laporan Keuangan Tahun 2023/Audit/WINE/Perubahan Aset dan Liabilitas LD 20 pct.pdf",
          "File_Size": 682602,
          "File_Type": ".pdf",
          "Report_Period": "Audit",
          "Report_Type": "rdf",
          "Report_Year": "2023",
          "NamaEmiten": "PT Hatten Bali Tbk"
        },
        {
          "Emiten_Code": "WINE",
          "File_ID": "dd7edecf-0aa4-4e59-8dd8-31c7439b740e",
          "File_Modified": "2024-03-26T17:00:11.637",
          "File_Name": "FinancialStatement-2023-Tahunan-WINE.xlsx",
          "File_Path": "/Portals/0/StaticData/ListedCompanies/Corporate_Actions/New_Info_JSX/Jenis_Informasi/01_Laporan_Keuangan/02_Soft_Copy_Laporan_Keuangan//Laporan Keuangan Tahun 2023/Audit/WINE/FinancialStatement-2023-Tahunan-WINE.xlsx",
          "File_Size": 154153,
          "File_Type": ".xlsx",
          "Report_Period": "Audit",
          "Report_Type": "rdf",
          "Report_Year": "2023",
          "NamaEmiten": "PT Hatten Bali Tbk"
        },
        {
          "Emiten_Code": "WINE",
          "File_ID": "7ef8e564-c64b-4f1d-999e-38544c6e46d6",
          "File_Modified": "2024-03-26T17:00:11.637",
          "File_Name": "LK Per 31 Desember 2023 - WINE.pdf",
          "File_Path": "/Portals/0/StaticData/ListedCompanies/Corporate_Actions/New_Info_JSX/Jenis_Informasi/01_Laporan_Keuangan/02_Soft_Copy_Laporan_Keuangan//Laporan Keuangan Tahun 2023/Audit/WINE/LK Per 31 Desember 2023 - WINE.pdf",
          "File_Size": 6027759,
          "File_Type": ".pdf",
          "Report_Period": "Audit",
          "Report_Type": "rdf",
          "Report_Year": "2023",
          "NamaEmiten": "PT Hatten Bali Tbk"
        },
        {
          "Emiten_Code": "WINE",
          "File_ID": "a2c80fba-89cd-41d9-ace8-64abaa8ce7ac",
          "File_Modified": "2024-03-26T17:00:11.637",
          "File_Name": "AnnualReport2023-WINE-att1.pdf",
          "File_Path": "/Portals/0/StaticData/NewsAndAnnouncement/ANNOUNCEMENTSTOCK/From_EREP/202404/3677a03791_9d40084f7c.pdf",
          "File_Size": 0,
          "File_Type": ".pdf",
          "Report_Period": "Audit",
          "Report_Type": "rdf",
          "Report_Year": "2023",
          "NamaEmiten": "PT Hatten Bali Tbk"
        },
        {
          "Emiten_Code": "WINE",
          "File_ID": "4f2d33c9-3ff7-4a53-9e7f-875618ca7cfe",
          "File_Modified": "2024-03-26T17:00:11.637",
          "File_Name": "Checklist Pengungkapan LK Tahunan 2023.pdf",
          "File_Path": "/Portals/0/StaticData/ListedCompanies/Corporate_Actions/New_Info_JSX/Jenis_Informasi/01_Laporan_Keuangan/02_Soft_Copy_Laporan_Keuangan//Laporan Keuangan Tahun 2023/Audit/WINE/Checklist Pengungkapan LK Tahunan 2023.pdf",
          "File_Size": 3438175,
          "File_Type": ".pdf",
          "Report_Period": "Audit",
          "Report_Type": "rdf",
          "Report_Year": "2023",
          "NamaEmiten": "PT Hatten Bali Tbk"
        },
        {
          "Emiten_Code": "WINE",
          "File_ID": "19e731b0-ebe1-4052-917b-a6d736de0f9e",
          "File_Modified": "2024-03-26T17:00:11.637",
          "File_Name": "Surat Pernyataan Direksi.pdf",
          "File_Path": "/Portals/0/StaticData/ListedCompanies/Corporate_Actions/New_Info_JSX/Jenis_Informasi/01_Laporan_Keuangan/02_Soft_Copy_Laporan_Keuangan//Laporan Keuangan Tahun 2023/Audit/WINE/Surat Pernyataan Direksi.pdf",
          "File_Size": 684025,
          "File_Type": ".pdf",
          "Report_Period": "Audit",
          "Report_Type": "rdf",
          "Report_Year": "2023",
          "NamaEmiten": "PT Hatten Bali Tbk"
        },
        {
          "Emiten_Code": "WINE",
          "File_ID": "0181b036-56d9-4ee1-97aa-bbc3027f20f9",
          "File_Modified": "2024-03-26T17:00:11.637",
          "File_Name": "Surat Pengantar LK - WINE.pdf",
          "File_Path": "/Portals/0/StaticData/ListedCompanies/Corporate_Actions/New_Info_JSX/Jenis_Informasi/01_Laporan_Keuangan/02_Soft_Copy_Laporan_Keuangan//Laporan Keuangan Tahun 2023/Audit/WINE/Surat Pengantar LK - WINE.pdf",
          "File_Size": 683321,
          "File_Type": ".pdf",
          "Report_Period": "Audit",
          "Report_Type": "rdf",
          "Report_Year": "2023",
          "NamaEmiten": "PT Hatten Bali Tbk"
        },
        {
          "Emiten_Code": "WINE",
          "File_ID": "99fc7a84-7802-49dd-b193-c56aa87cb851",
          "File_Modified": "2024-03-26T17:00:11.637",
          "File_Name": "AnnualReport2023-WINE-att3.pdf",
          "File_Path": "/Portals/0/StaticData/NewsAndAnnouncement/ANNOUNCEMENTSTOCK/From_EREP/202404/e9b821b1e1_9e8b7fc798.pdf",
          "File_Size": 0,
          "File_Type": ".pdf",
          "Report_Period": "Audit",
          "Report_Type": "rdf",
          "Report_Year": "2023",
          "NamaEmiten": "PT Hatten Bali Tbk"
        },
        {
          "Emiten_Code": "WINE",
          "File_ID": "106a7574-11a7-48e9-8740-73607965629b",
          "File_Modified": "2024-03-26T17:00:11.637",
          "File_Name": "FinancialStatement-2023-Tahunan-WINE.pdf",
          "File_Path": "/Portals/0/StaticData/ListedCompanies/Corporate_Actions/New_Info_JSX/Jenis_Informasi/01_Laporan_Keuangan/02_Soft_Copy_Laporan_Keuangan//Laporan Keuangan Tahun 2023/Audit/WINE/FinancialStatement-2023-Tahunan-WINE.pdf",
          "File_Size": 715510,
          "File_Type": ".pdf",
          "Report_Period": "Audit",
          "Report_Type": "rdf",
          "Report_Year": "2023",
          "NamaEmiten": "PT Hatten Bali Tbk"
        },
        {
          "Emiten_Code": "WINE",
          "File_ID": "9c6659a1-1481-4573-adb1-093cd025d93d",
          "File_Modified": "2024-03-26T17:00:11.637",
          "File_Name": "AnnualReport2023-WINE.pdf",
          "File_Path": "/Portals/0/StaticData/NewsAndAnnouncement/ANNOUNCEMENTSTOCK/From_EREP/202404/b8dbfacf67_c4469e9c90.pdf",
          "File_Size": 0,
          "File_Type": ".pdf",
          "Report_Period": "Audit",
          "Report_Type": "rdf",
          "Report_Year": "2023",
          "NamaEmiten": "PT Hatten Bali Tbk"
        },
        {
          "Emiten_Code": "WINE",
          "File_ID": "af1d0575-a6f1-42e8-ab5b-1012e70721eb",
          "File_Modified": "2024-03-26T17:00:11.637",
          "File_Name": "inlineXBRL.zip",
          "File_Path": "/Portals/0/StaticData/ListedCompanies/Corporate_Actions/New_Info_JSX/Jenis_Informasi/01_Laporan_Keuangan/02_Soft_Copy_Laporan_Keuangan//Laporan Keuangan Tahun 2023/Audit/WINE/inlineXBRL.zip",
          "File_Size": 261987,
          "File_Type": ".zip",
          "Report_Period": "Audit",
          "Report_Type": "rdf",
          "Report_Year": "2023",
          "NamaEmiten": "PT Hatten Bali Tbk"
        },
        {
          "Emiten_Code": "WINE",
          "File_ID": "02242fef-1f46-4f3e-adef-75832273b7bc",
          "File_Modified": "2024-03-26T17:00:11.637",
          "File_Name": "AnnualReport2023-WINE-att2.pdf",
          "File_Path": "/Portals/0/StaticData/NewsAndAnnouncement/ANNOUNCEMENTSTOCK/From_EREP/202404/46d1e02a6d_c789e42952.pdf",
          "File_Size": 0,
          "File_Type": ".pdf",
          "Report_Period": "Audit",
          "Report_Type": "rdf",
          "Report_Year": "2023",
          "NamaEmiten": "PT Hatten Bali Tbk"
        },
        {
          "Emiten_Code": "WINE",
          "File_ID": "beb2695d-0ff6-4957-9246-f02bd8aaeef8",
          "File_Modified": "2024-03-26T17:00:11.637",
          "File_Name": "instance.zip",
          "File_Path": "/Portals/0/StaticData/ListedCompanies/Corporate_Actions/New_Info_JSX/Jenis_Informasi/01_Laporan_Keuangan/02_Soft_Copy_Laporan_Keuangan//Laporan Keuangan Tahun 2023/Audit/WINE/instance.zip",
          "File_Size": 140303,
          "File_Type": ".zip",
          "Report_Period": "Audit",
          "Report_Type": "rdf",
          "Report_Year": "2023",
          "NamaEmiten": "PT Hatten Bali Tbk"
        }
      ]
    }
  ]
}